carthorse/__init__.py
carthorse/actions.py
carthorse/cli.py
carthorse/config.py
carthorse/plugins.py
carthorse/version_from.py
carthorse/when.py
carthorse-2.0.3.dist-info/LICENSE.txt
carthorse-2.0.3.dist-info/METADATA
carthorse-2.0.3.dist-info/WHEEL
carthorse-2.0.3.dist-info/entry_points.txt
carthorse-2.0.3.dist-info/top_level.txt
carthorse-2.0.3.dist-info/RECORD
