Metadata-Version: 2.2
Name: carthorse
Version: 2.0.3
Summary: Safely creating releases when you change the version number.
Home-page: https://github.com/cjw296/carthorse
Author: Chris Withers
Author-email: chris@withers.org
License: MIT
Classifier: License :: OSI Approved :: MIT License
Classifier: Programming Language :: Python :: 3
Classifier: Programming Language :: Python :: 3.12
Classifier: Programming Language :: Python :: 3.13
Requires-Python: >=3.12
License-File: LICENSE.txt
Requires-Dist: pyyaml
Requires-Dist: toml
Provides-Extra: test
Requires-Dist: pytest; extra == "test"
Requires-Dist: pytest-cov; extra == "test"
Requires-Dist: sybil>=4; extra == "test"
Requires-Dist: testfixtures; extra == "test"
Provides-Extra: build
Requires-Dist: twine; extra == "build"
Requires-Dist: wheel; extra == "build"
Dynamic: author
Dynamic: author-email
Dynamic: classifier
Dynamic: description
Dynamic: home-page
Dynamic: license
Dynamic: provides-extra
Dynamic: requires-dist
Dynamic: requires-python
Dynamic: summary
